sword_converter/__init__.py
sword_converter/__main__.py
sword_converter/converters/__init__.py
sword_converter/converters/bible.py
sword_converter/utils/__init__.py
sword_converter/utils/metadata.py
sword_converter/utils/progress.py
sword_converter-2.0.0.dist-info/COPYING
sword_converter-2.0.0.dist-info/METADATA
sword_converter-2.0.0.dist-info/WHEEL
sword_converter-2.0.0.dist-info/entry_points.txt
sword_converter-2.0.0.dist-info/RECORD
