Metadata-Version: 2.1
Name: sword-converter
Version: 2.0.0
Summary: Generate JSON Files and SQLite Databases of Bible Texts from SWORD Modules
Home-page: https://github.com/evnskc/sword-converter
License: GPL-3.0-or-later
Keywords: SWORD,Converter,Bible Text,JSON,SQLite
Author: Evans
Author-email: evans@fundi.dev
Requires-Python: >=3.10,<4.0
Classifier: License :: OSI Approved :: GNU General Public License v3 or later (GPLv3+)
Classifier: Programming Language :: Python :: 3
Classifier: Programming Language :: Python :: 3.10
Classifier: Programming Language :: Python :: 3.11
Classifier: Programming Language :: Python :: 3.12
Requires-Dist: pysword (>=0.2.8,<0.3.0)
Project-URL: Documentation, https://github.com/evnskc/sword-converter
Project-URL: Repository, https://github.com/evnskc/sword-converter
